tfquery/__init__.py
tfquery/__main__.py
tfquery/sql_handler.py
tfquery/tfstate.py
tfquery/tfstate_v3_migration.py
tfquery/utils.py
tfquery-0.0.2.dist-info/LICENSE.md
tfquery-0.0.2.dist-info/METADATA
tfquery-0.0.2.dist-info/WHEEL
tfquery-0.0.2.dist-info/entry_points.txt
tfquery-0.0.2.dist-info/top_level.txt
tfquery-0.0.2.dist-info/RECORD
