Metadata-Version: 2.1
Name: tfquery
Version: 0.0.2
Summary: tfquery: Run SQL queries on your Terraform infrastructure. Query resources and analyze its configuration using a SQL-powered framework.
Home-page: http://github.com/mazen160/tfquery
Author: Mazin Ahmed
Author-email: mazin@mazinahmed.net
License: LICENSE.md
Platform: UNKNOWN
